setux/modules/admin.py
setux/modules/autotest.py
setux/modules/copy_id.py
setux/modules/download.py
setux/modules/infos.py
setux/modules/ping.py
setux/modules/prepare.py
setux/modules/sudoers.py
setux/modules/upd_cfg.py
setux_modules-0.2504.0.dist-info/METADATA
setux_modules-0.2504.0.dist-info/WHEEL
setux_modules-0.2504.0.dist-info/top_level.txt
setux_modules-0.2504.0.dist-info/RECORD
