Metadata-Version: 2.2
Name: setux_modules
Version: 0.2504.0
Summary: System deployment
Author-email: Louis RIVIERE <louis@riviere.xyz>
Maintainer-email: Louis RIVIERE <louis@riviere.xyz>
License: MIT
Project-URL: Homepage, https://pypi.org/project/setux-modules
Project-URL: pypi, https://pypi.org/project/setux-modules
Project-URL: repository, https://bitbucket.org/dugres/setux_modules
Project-URL: Documentation, https://setux-modules.readthedocs.io
Keywords: utility
Classifier: Development Status :: 3 - Alpha
Classifier: License :: OSI Approved :: MIT License
Classifier: Programming Language :: Python :: 3
Classifier: Operating System :: POSIX :: Linux
Classifier: Environment :: Console
Classifier: Intended Audience :: Developers
Classifier: Intended Audience :: Information Technology
Classifier: Intended Audience :: System Administrators
Classifier: Topic :: System :: Installation/Setup
Classifier: Topic :: System :: Systems Administration
Classifier: Topic :: Utilities
Requires-Dist: setux_core>=0.2503.2
